spyod/__init__.py
spyod/findpairs.py
spyod/spod.py
SPyOD-0.1.7.dist-info/LICENSE
SPyOD-0.1.7.dist-info/METADATA
SPyOD-0.1.7.dist-info/WHEEL
SPyOD-0.1.7.dist-info/top_level.txt
SPyOD-0.1.7.dist-info/RECORD
