Metadata-Version: 2.1
Name: SPyOD
Version: 0.1.7
Summary: Spectral Proper Orthogonal Decomposition
Author-email: Grigorios Hatzissawidis <grigorios.hatzissawidis@fst.tu-darmstadt.de>, Moritz Sieber <moritz.sieber@tu-berlin.de>
Project-URL: Homepage, https://github.com/grigorishat/SPyOD
Classifier: Programming Language :: Python :: 3
Classifier: License :: OSI Approved :: MIT License
Classifier: Operating System :: OS Independent
Requires-Python: >=3.7
License-File: LICENSE
